{
    "peliculas": [
      {
        "id": 1,
        "nombre": "El sexto sentido",
        "director": "M. Night Shyamalan",
        "clasificacion": "Drama",
        "url": "https://raw.githubusercontent.com/monteromario/api/master/1.jpg"
      },
      {
        "id": 2,
        "nombre": "Pulp Fiction",
        "director": "Tarantino",
        "clasificacion": "Acción",
        "url": "https://raw.githubusercontent.com/monteromario/api/master/2.jpg"      },
      {
        "id": 3,
        "nombre": "Todo Sobre Mi Madre",
        "director": "Almodobar",
        "clasificacion": "Drama",
        "url": "https://raw.githubusercontent.com/monteromario/api/master/3.jpg"      },
      {
        "id": 4,
        "nombre": "300",
        "director": "Zack Snyder",
        "clasificacion": "Acción",
        "url": "https://raw.githubusercontent.com/monteromario/api/master/4.jpg"      },
      {
        "id": 5,
        "nombre": "El silencio de los corderos",
        "director": "Jonathan Demme",
        "clasificacion": "Drama",
        "url": "https://raw.githubusercontent.com/monteromario/api/master/5.jpg"      },
      {
        "id": 6,
        "nombre": "Forrest Gump",
        "director": "Robert Zemeckis",
        "clasificacion": "Comedia",
        "url": "https://raw.githubusercontent.com/monteromario/api/master/6.jpg"      },
      {
        "id": 7,
        "nombre": "Las Hurdes",
        "director": "Luis Buñuel",
        "clasificacion": "Documental",
        "url": "https://raw.githubusercontent.com/monteromario/api/master/7.jpg"      }
    ]
  }